README.org
jaglar/__init__.py
jaglar/cli.py
jaglar/ganttpro.py
jaglar/tj.py
jaglar/types.py
jaglar/utils.py
jaglar-0.1.0.dist-info/entry_points.txt
jaglar-0.1.0.dist-info/WHEEL
jaglar-0.1.0.dist-info/METADATA
jaglar-0.1.0.dist-info/RECORD
