Metadata-Version: 2.1
Name: jaglar
Version: 0.1.0
Summary: Tool for project management backed by taskjuggler.
Home-page: https://github.com/Vernacular-ai/jaglar/
License: GPL-3.0-only
Author: Abhinav Tushar
Author-email: abhinav@lepisma.xyz
Requires-Python: >=3.8,<4.0
Classifier: License :: OSI Approved :: GNU General Public License v3 (GPLv3)
Classifier: Programming Language :: Python :: 3
Classifier: Programming Language :: Python :: 3.8
Requires-Dist: docopt (>=0.6.2,<0.7.0)
Requires-Dist: pandas (>=1.0.3,<2.0.0)
Requires-Dist: pydash (>=4.7.6,<5.0.0)
Requires-Dist: xlrd (>=1.2.0,<2.0.0)
Requires-Dist: xmljson (>=0.2.0,<0.3.0)
Project-URL: Repository, https://github.com/Vernacular-ai/jaglar/
